pytaraxa/__init__.py
pytaraxa/admin/__init__.py
pytaraxa/admin/methods.py
pytaraxa/admin_net/__init__.py
pytaraxa/admin_net/methods.py
pytaraxa/debug/__init__.py
pytaraxa/eth/__init__.py
pytaraxa/eth/methods.py
pytaraxa/jsonrpc/__init__.py
pytaraxa/jsonrpc/_http.py
pytaraxa/jsonrpc/_websocket.py
pytaraxa/jsonrpc/http_eth.py
pytaraxa/jsonrpc/http_net.py
pytaraxa/jsonrpc/http_taraxa.py
pytaraxa/jsonrpc/http_web3.py
pytaraxa/jsonrpc/utl.py
pytaraxa/net/__init__.py
pytaraxa/net/methods.py
pytaraxa/taraxa/__init__.py
pytaraxa/taraxa/methods.py
pytaraxa/test/__init__.py
pytaraxa/test/creat_conf.py
pytaraxa/test/test.py
pytaraxa/test/test2.py
pytaraxa/web3/__init__.py
pytaraxa/web3/methods.py
pytaraxa/web3/web3.py
script/read.py
test/test_net.py
test/test_test.py
test/test_web3.py
pytaraxa-0.0.4.dist-info/LICENSE
pytaraxa-0.0.4.dist-info/METADATA
pytaraxa-0.0.4.dist-info/WHEEL
pytaraxa-0.0.4.dist-info/top_level.txt
pytaraxa-0.0.4.dist-info/zip-safe
pytaraxa-0.0.4.dist-info/RECORD
