Metadata-Version: 2.1
Name: pytaraxa
Version: 0.0.4
Summary: Taraxa blockchain  RPC client.
Home-page: http://taraxa.io
Author: Aeneas
Author-email: kai.he@taraxa.io
License: MIT
Keywords: Taraxa blockchain RPC client
Platform: UNKNOWN
Classifier: License :: OSI Approved :: MIT License
Classifier: Programming Language :: Python
Classifier: Intended Audience :: Developers
Classifier: Operating System :: OS Independent
Requires-Python: >=3.7
